README.rst
setup.py
boavus/VERSION
boavus/__init__.py
boavus/bidso.py
boavus/command.py
boavus/utils.py
boavus.egg-info/PKG-INFO
boavus.egg-info/SOURCES.txt
boavus.egg-info/dependency_links.txt
boavus.egg-info/entry_points.txt
boavus.egg-info/requires.txt
boavus.egg-info/top_level.txt
boavus/corr/__init__.py
boavus/corr/corrfmri.py
boavus/corr/summary.py
boavus/electrodes/__init__.py
boavus/electrodes/assign_regions.py
boavus/electrodes/plot.py
boavus/electrodes/project_to_surf.py
boavus/electrodes/elec/__init__.py
boavus/electrodes/elec/annealing.py
boavus/fmri/__init__.py
boavus/fmri/at_electrodes.py
boavus/fmri/compare.py
boavus/fmri/utils.py
boavus/fsl/__init__.py
boavus/fsl/coreg.py
boavus/fsl/feat.py
boavus/fsl/feat_on_surf.py
boavus/fsl/misc.py
boavus/ieeg/__init__.py
boavus/ieeg/broadband.py
boavus/ieeg/compare.py
boavus/ieeg/preprocessing.py
boavus/ieeg/psd.py
boavus/ieeg/read.py
boavus/ieeg/utils.py
boavus/mri/__init__.py
boavus/mri/surface.py
boavus/prf/__init__.py
boavus/prf/fit.py
boavus/prf/core/__init__.py
boavus/prf/core/least_squares.py
boavus/prf/core/popeye.py
boavus/workflow/__init__.py
boavus/workflow/corr_ieeg_fmri.py
boavus/workflow/fmri.py
boavus/workflow/ieeg.py
tests/__init__.py
tests/paths.py
tests/test_20_workflow_ieeg.py
tests/test_21_workflow_fmri.py
tests/test_22_workflow_grvx.py
tests/utils.py