Metadata-Version: 2.1
Name: boavus
Version: 0.4
Summary: Tools to analyze data structured as BIDS in Python
Home-page: https://github.com/gpiantoni/boavus
Author: Gio Piantoni
Author-email: boavus@gpiantoni.com
License: MIT
Keywords: bids
Platform: UNKNOWN
Classifier: Development Status :: 2 - Pre-Alpha
Classifier: Intended Audience :: Healthcare Industry
Classifier: Intended Audience :: Science/Research
Classifier: Topic :: Scientific/Engineering :: Bio-Informatics
Classifier: Topic :: Scientific/Engineering :: Medical Science Apps.
Classifier: License :: OSI Approved :: MIT License
Classifier: Programming Language :: Python :: 3 :: Only
Classifier: Programming Language :: Python :: 3.6
Provides-Extra: test
